ek_ctp/__init__.py
ek_ctp/api/__init__.py
ek_ctp/api/ctp_constant.py
ek_ctp/api/libthostmduserapi_se.so
ek_ctp/api/libthosttraderapi_se.so
ek_ctp/api/thostmduserapi_se.dll
ek_ctp/api/thosttraderapi_se.dll
ek_ctp/api/vnctpmd.cp310-win_amd64.pyd
ek_ctp/api/vnctptd.cp310-win_amd64.pyd
ek_ctp/api/generator/ctp_constant.py
ek_ctp/api/generator/ctp_md_header_define.h
ek_ctp/api/generator/ctp_md_header_function.h
ek_ctp/api/generator/ctp_md_header_on.h
ek_ctp/api/generator/ctp_md_header_process.h
ek_ctp/api/generator/ctp_md_source_function.cpp
ek_ctp/api/generator/ctp_md_source_module.cpp
ek_ctp/api/generator/ctp_md_source_on.cpp
ek_ctp/api/generator/ctp_md_source_process.cpp
ek_ctp/api/generator/ctp_md_source_switch.cpp
ek_ctp/api/generator/ctp_md_source_task.cpp
ek_ctp/api/generator/ctp_struct.py
ek_ctp/api/generator/ctp_td_header_define.h
ek_ctp/api/generator/ctp_td_header_function.h
ek_ctp/api/generator/ctp_td_header_on.h
ek_ctp/api/generator/ctp_td_header_process.h
ek_ctp/api/generator/ctp_td_source_function.cpp
ek_ctp/api/generator/ctp_td_source_module.cpp
ek_ctp/api/generator/ctp_td_source_on.cpp
ek_ctp/api/generator/ctp_td_source_process.cpp
ek_ctp/api/generator/ctp_td_source_switch.cpp
ek_ctp/api/generator/ctp_td_source_task.cpp
ek_ctp/api/generator/ctp_typedef.py
ek_ctp/api/generator/generate_api_functions.py
ek_ctp/api/generator/generate_data_type.py
ek_ctp/api/generator/generate_struct.py
ek_ctp/api/include/ctp/ThostFtdcMdApi.h
ek_ctp/api/include/ctp/ThostFtdcTraderApi.h
ek_ctp/api/include/ctp/ThostFtdcUserApiDataType.h
ek_ctp/api/include/ctp/ThostFtdcUserApiStruct.h
ek_ctp/api/include/mac/ctp/ThostFtdcMdApi.h
ek_ctp/api/include/mac/ctp/ThostFtdcTraderApi.h
ek_ctp/api/include/mac/ctp/ThostFtdcUserApiDataType.h
ek_ctp/api/include/mac/ctp/ThostFtdcUserApiStruct.h
ek_ctp/api/include/mac/pybind11/attr.h
ek_ctp/api/include/mac/pybind11/buffer_info.h
ek_ctp/api/include/mac/pybind11/cast.h
ek_ctp/api/include/mac/pybind11/chrono.h
ek_ctp-6.6.7.6.dist-info/LICENSE
ek_ctp-6.6.7.6.dist-info/METADATA
ek_ctp-6.6.7.6.dist-info/WHEEL
ek_ctp-6.6.7.6.dist-info/top_level.txt
ek_ctp-6.6.7.6.dist-info/RECORD
