Metadata-Version: 2.1
Name: ek-ctp
Version: 6.6.7.6
Summary: CTP gateway for bothpy quant trading framework.
License: MIT
Keywords: quant,quantitative,investment,trading,algotrading,ctp
Classifier: Development Status :: 5 - Production/Stable
Classifier: Operating System :: Microsoft :: Windows
Classifier: Operating System :: POSIX :: Linux
Classifier: Operating System :: MacOS
Classifier: Programming Language :: Python :: 3
Classifier: Programming Language :: Python :: 3.7
Classifier: Programming Language :: Python :: 3.8
Classifier: Programming Language :: Python :: 3.9
Classifier: Programming Language :: Python :: 3.10
Classifier: Topic :: Office/Business :: Financial :: Investment
Classifier: Programming Language :: Python :: Implementation :: CPython
Classifier: License :: OSI Approved :: MIT License
Classifier: Natural Language :: Chinese (Simplified)
Requires-Python: >=3.7
License-File: LICENSE
Requires-Dist: importlib-metadata
